{
  "Version": 3,
  "Meta": {
    "Duration": 2.7,
    "Fps": 30.0,
    "Loop": true,
    "AreBeziersRestricted": true,
    "CurveCount": 6,
    "TotalSegmentCount": 20,
    "TotalPointCount": 24,
    "UserDataCount": 1,
    "TotalUserDataSize": 0
  },
  "Curves": [
    {
      "Target": "Parameter",
      "Id": "ParamMouthForm",
      "Segments": [
        0,
        0,
        0,
        0.267,
        -0.6,
        2,
        1.233,
        -0.6,
        0,
        1.467,
        -0.7,
        1,
        1.834,
        -0.7,
        2.2,
        -0.622,
        2.567,
        -0.4,
        1,
        2.611,
        -0.373,
        2.656,
        0,
        2.7,
        0
      ]
    },
    {
      "Target": "Parameter",
      "Id": "ParamMouthOpenY",
      "Segments": [
        0,
        0,
        0,
        0.267,
        0.3,
        0,
        0.5,
        0.1,
        0,
        0.733,
        0.4,
        0,
        0.967,
        0.2,
        0,
        1.233,
        0.5,
        0,
        1.467,
        0,
        0,
        1.733,
        0.5,
        0,
        2.033,
        0.1,
        0,
        2.333,
        0.5,
        0,
        2.7,
        0
      ]
    },
    {
      "Target": "Parameter",
      "Id": "Param74",
      "Segments": [
        0,
        0,
        0,
        2.7,
        0
      ]
    },
    {
      "Target": "Parameter",
      "Id": "Param75",
      "Segments": [
        0,
        0,
        0,
        2.7,
        0
      ]
    },
    {
      "Target": "Parameter",
      "Id": "Param79",
      "Segments": [
        0,
        0,
        0,
        2.7,
        0
      ]
    },
    {
      "Target": "Parameter",
      "Id": "Param80",
      "Segments": [
        0,
        0,
        0,
        2.7,
        0
      ]
    }
  ],
  "UserData": [
    {
      "Time": 0.0,
      "Value": ""
    }
  ]
}